{
 "@context": "https://w3id.org/ro/crate/1.1/context",
 "@graph": [
  {
   "@id": "./",
   "@type": "Dataset",
   "datePublished": "2025-08-03T01:40:24+00:00",
   "hasPart": [
    {
     "@id": "tidal_correction.ipynb"
    },
    {
     "@id": "code_blocks/cell_1.py"
    },
    {
     "@id": "code_blocks/cell_2.py"
    },
    {
     "@id": "code_blocks/cell_3.py"
    },
    {
     "@id": "code_blocks/cell_4.py"
    },
    {
     "@id": "code_blocks/cell_5.py"
    },
    {
     "@id": "code_blocks/cell_6.py"
    },
    {
     "@id": "code_blocks/cell_7.py"
    },
    {
     "@id": "code_blocks/cell_8.py"
    },
    {
     "@id": "code_blocks/cell_9.py"
    }
   ],
   "mainEntity": {"@id": "tidal_correction.ipynb"},
   "name": "Notebook Provenance Crate (tidal_correction.ipynb)"
  },
  {
   "@id": "ro-crate-metadata.json",
   "@type": "CreativeWork",
   "about": {"@id": "./"},
   "conformsTo": {"@id": "https://w3id.org/ro/crate/1.1"}
  },
  {
   "@id": "tidal_correction.ipynb",
   "@type": ["File", "SoftwareSourceCode", "HowTo"],
   "input": [
    {
     "@id": "#fp-polygons_geojson"
    },
    {
     "@id": "#fp-tides_csv"
    },
    {
     "@id": "#fp-transect_time_series_csv"
    },
    {
     "@id": "#fp-transects_extended_geojson"
    }
   ],
   "output": [
    {
     "@id": "#fp-tides_csv"
    },
    {
     "@id": "#fp-transect_time_series_tidally_corrected_csv"
    }
   ],
   "step": "... 9 steps ...",
   "targetProduct": {"@id": "#jupyter-kernel"}
  },
  {
   "@id": "#jupyter-kernel",
   "@type": "SoftwareApplication",
   "description": "Jupyter Notebook kernel for Python 3",
   "identifier": "python3",
   "name": "Jupyter Notebook Kernel",
   "programmingLanguage": "python3",
   "softwareVersion": "3.12.3",
   "version": "3.12.3"
  },
  {
   "@id": "#step-1",
   "@type": "HowToStep",
   "about": {"@id": "#create-action-1"},
   "name": "Code cell 1",
   "position": 1,
   "tool": {"@id": "#jupyter-kernel"},
   "workExample": {"@id": "code_blocks/cell_1.py"}
  },
  {
   "@id": "#step-2",
   "@type": "HowToStep",
   "about": {"@id": "#create-action-2"},
   "name": "Code cell 2",
   "position": 2,
   "tool": {"@id": "#jupyter-kernel"},
   "workExample": {"@id": "code_blocks/cell_2.py"}
  },
  {
   "@id": "... workflow steps ...",
   "@type": "HowToStepSummary",
   "count": 5,
   "position_range": [
    3,
    7
   ],
   "step_pattern": "Code cell 3 to Code cell 7",
   "tools_used": ["#jupyter-kernel"],
   "actions_referenced": 9,
   "note": "Collapsed 5 middle HowToStep entities (showing first 2 and last 2)"
  },
  {
   "@id": "#step-8",
   "@type": "HowToStep",
   "about": {"@id": "#create-action-8"},
   "name": "Code cell 8",
   "position": 8,
   "tool": {"@id": "#jupyter-kernel"},
   "workExample": {"@id": "code_blocks/cell_8.py"}
  },
  {
   "@id": "#step-9",
   "@type": "HowToStep",
   "about": {"@id": "#create-action-9"},
   "name": "Code cell 9",
   "position": 9,
   "tool": {"@id": "#jupyter-kernel"},
   "workExample": {"@id": "code_blocks/cell_9.py"}
  },
  {
   "@id": "#fp-tides_csv",
   "@type": "FormalParameter",
   "name": "tides.csv"
  },
  {
   "@id": "#fp-transect_time_series_csv",
   "@type": "FormalParameter",
   "name": "transect_time_series.csv"
  },
  {
   "@id": "#fp-transect_time_series_tidally_corrected_csv",
   "@type": "FormalParameter",
   "name": "transect_time_series_tidally_corrected.csv"
  },
  {
   "@id": "#fp-polygons_geojson",
   "@type": "FormalParameter",
   "name": "polygons.geojson"
  },
  {
   "@id": "#fp-transects_extended_geojson",
   "@type": "FormalParameter",
   "name": "transects_extended.geojson"
  },
  {
   "@id": "#create-action-1",
   "@type": "CreateAction",
   "instrument": {"@id": "code_blocks/cell_1.py"}
  },
  {
   "@id": "#create-action-2",
   "@type": "CreateAction",
   "instrument": {"@id": "code_blocks/cell_2.py"}
  },
  {
   "@id": "#create-action-3",
   "@type": "CreateAction",
   "instrument": {"@id": "code_blocks/cell_3.py"}
  },
  {
   "@id": "... create actions ...",
   "count": 3,
   "note": "Showing first 3 and last 3 of 9 CreateActions"
  },
  {
   "@id": "#create-action-7",
   "@type": "CreateAction",
   "instrument": {"@id": "code_blocks/cell_7.py"}
  },
  {
   "@id": "#create-action-8",
   "@type": "CreateAction",
   "instrument": {"@id": "code_blocks/cell_8.py"}
  },
  {
   "@id": "#create-action-9",
   "@type": "CreateAction",
   "instrument": {"@id": "code_blocks/cell_9.py"}
  },
  {
   "@id": "... code cells ...",
   "count": 9,
   "input_distribution": {
    "0": 3,
    "1": 5,
    "2": 1
   },
   "output_distribution": {
    "0": 7,
    "1": 1,
    "2": 1
   }
  }
 ]
}